pydictionary/__init__.py
pydictionary/dictionary.py
Py_Dictionary-4.1.4.dist-info/METADATA
Py_Dictionary-4.1.4.dist-info/WHEEL
Py_Dictionary-4.1.4.dist-info/top_level.txt
Py_Dictionary-4.1.4.dist-info/RECORD
