Metadata-Version: 2.1
Name: Py-Dictionary
Version: 4.1.4
Summary: Dictionary module
Home-page: https://github.com/nit-in/py-dictionary
Author: nit-in
Author-email: nit_in@live.com
License: UNKNOWN
Platform: UNKNOWN
Classifier: Programming Language :: Python :: 3
Classifier: Operating System :: OS Independent
